{"type": "Feature", "id": 12523872, "geometry": {"type": "Point", "coordinates": [23.152969, 37.26556]}, "properties": {"woe:id": 12523872, "woe:parent_id": 962715, "woe:name": "Spetsai Airport", "woe:placetype": 14, "woe:placetype_name": "Airport", "woe:lang": "ENG", "iso:country": "GR", "meta:provider": ["geoplanet:7.3.1", "geoplanet:7.3.2", "geoplanet:7.4.0", "geoplanet:7.4.1", "geoplanet:7.5.1", "geoplanet:7.5.2", "geoplanet:7.6.0", "geoplanet:7.8.1", "geoplanet:7.9.0", "geoplanet:7.10.0", "geoplanet:8.0.0", "woeplanet:8.0.0"], "meta:indexed": "2020-08-20T20:51:58.035316", "woe:alias_ENG_V": ["JSS Airport", "JSS"], "meta:updated": "2020-10-14T10:59:17.882398", "woe:hierarchy": {"continent": 24865675, "country": 23424833, "town": 0, "planet": 1, "county": 12577879, "suburb": 0, "state": 56558063, "region": 0, "localadmin": 24544103}, "woe:timezone_id": 28350888, "woe:hash": "sw87yzgrx7bu", "woe:centroid": [23.152969, 37.26556], "geom:latitude": 37.26556, "geom:longitude": 23.152969, "geom:hash": "sw87yzgrx7bu", "woe:latitude": 37.26556, "geom:centroid": [23.152969, 37.26556], "woe:longitude": 23.152969, "woe:repo": "woeplanet-airport-gr", "geom:area": 0.0, "woe:scale": 19}}