{"type": "Feature", "id": 12523873, "geometry": {"type": "Point", "coordinates": [21.75, 37.75]}, "properties": {"woe:id": 12523873, "woe:parent_id": 960495, "woe:name": "Pyrgos Airport", "woe:placetype": 14, "woe:placetype_name": "Airport", "woe:lang": "ENG", "iso:country": "GR", "meta:provider": ["geoplanet:7.3.1", "geoplanet:7.3.2", "geoplanet:7.4.0", "geoplanet:7.4.1", "geoplanet:7.5.1", "geoplanet:7.5.2", "geoplanet:7.6.0", "geoplanet:7.8.1", "geoplanet:7.9.0", "geoplanet:7.10.0", "geoplanet:8.0.0", "woeplanet:8.0.0"], "meta:indexed": "2020-08-20T20:51:58.036244", "woe:alias_ENG_V": ["PYR Airport", "PYR"], "meta:updated": "2020-10-14T10:59:17.882918", "woe:hierarchy": {"continent": 24865675, "country": 23424833, "town": 0, "planet": 1, "county": 12577880, "suburb": 0, "state": 56558068, "region": 0, "localadmin": 56558341}, "woe:timezone_id": 28350888, "woe:hash": "sqxqybjvewp3", "woe:centroid": [21.75, 37.75], "geom:latitude": 37.75, "geom:longitude": 21.75, "geom:hash": "sqxqybjvewp3", "woe:latitude": 37.75, "geom:centroid": [21.75, 37.75], "woe:longitude": 21.75, "woe:repo": "woeplanet-airport-gr", "geom:area": 0.0, "woe:scale": 19}}