{"type": "Feature", "id": 12513306, "properties": {"woe:id": 12513306, "woe:parent_id": 959351, "woe:name": "Leros Airport", "woe:placetype": 14, "woe:placetype_name": "Airport", "woe:lang": "ENG", "iso:country": "GR", "meta:provider": ["geoplanet:7.3.1", "geoplanet:7.3.2", "geoplanet:7.4.0", "geoplanet:7.4.1", "geoplanet:7.5.1", "geoplanet:7.5.2", "geoplanet:7.6.0", "geoplanet:7.8.1", "geoplanet:7.9.0", "geoplanet:7.10.0", "geoplanet:8.0.0", "woeplanet:8.0.0"], "meta:indexed": "2020-08-20T20:51:58.005157", "woe:alias_ENG_V": ["LRS Airport", "LRS"], "meta:updated": "2020-08-22T01:54:33.612913", "woe:hierarchy": {"continent": 24865675, "country": 23424833, "town": 0, "planet": 1, "county": 12577886, "suburb": 0, "state": 56558069, "region": 0, "localadmin": 24544110}, "woe:timezone_id": 28350888, "woe:hash": "swe59ck2sfkx", "woe:centroid": [26.801701, 37.1847], "geom:latitude": 37.1847, "geom:longitude": 26.801701, "geom:hash": "swe59ck2sfkx", "woe:latitude": 37.1847, "geom:centroid": [26.801701, 37.1847], "woe:longitude": 26.801701, "woe:repo": "woeplanet-airport-gr"}, "geometry": {"coordinates": [26.801701, 37.1847], "type": "Point"}}